pyntensiswmp/__init__.py
pyntensiswmp-0.0.1.dist-info/METADATA
pyntensiswmp-0.0.1.dist-info/RECORD
pyntensiswmp-0.0.1.dist-info/WHEEL
pyntensiswmp-0.0.1.dist-info/top_level.txt
